Workbook

Sheet Savings Plan
A1: CAN WE AFFORD IT? — 20-MONTH SAVINGS PLAN
A2: Two earners, $0 saved today, departure in 20 months. All figures USD. Yellow cells are yours to change.
A4: INPUTS
A5: Gross salary — person A (USD/yr) | C5: 80000
A6: Gross salary — person B (USD/yr) | C6: 80000
A7: Effective tax rate (fed + state + FICA) | C7: 0.25
A8: Months until departure | C8: 20
A9: Living costs while renting (both, USD/mo) | C9: 4000
A10: Move aboard the boat at month # | C10: 10
A11: Living costs once aboard (both, USD/mo) | C11: 2200
A13: WHAT YOU EARN & CAN SAVE
A14: Combined gross income (USD/yr) | C14: =C5+C6 -> 160000
A15: Combined take-home (USD/yr) | C15: =C14*(1-C7) -> 120000
A16: Combined take-home (USD/mo) | C16: =C15/12 -> 10000
A17: Months renting before moving aboard | C17: =C10-1 -> 9
A18: Months living aboard before departure | C18: =C8-(C10-1) -> 11
A19: Savings/mo while renting | C19: =C16-C9 -> 6000
A20: Savings/mo while living aboard | C20: =C16-C11 -> 7800
A21: TOTAL SAVED BY DEPARTURE (this plan) | C21: =C17*C19+C18*C20 -> 139800
A24: IF YOU JUST PICK A MONTHLY SAVINGS TARGET INSTEAD
A25: Discipline level | B25: Saved/mo (both) | C25: Saved in 20 mo | D25: % of take-home
A26: Relaxed | B26: 2500 | C26: =B26*C$8 -> 50000 | D26: =B26/C$16 -> 0.25
A27: Committed | B27: 4000 | C27: =B27*C$8 -> 80000 | D27: =B27/C$16 -> 0.4
A28: Hardcore + liveaboard | B28: 6000 | C28: =B28*C$8 -> 120000 | D28: =B28/C$16 -> 0.6
A30: Bottom line: at a "Committed" ~$4,000/mo combined (about 40% of take-home) you bank ~$80k in 20 months — more than enough to float the trip and have a cushion. Smartest move: buy a cheap, sound boat ~10 months out, move aboard to kill rent, and use the time to fix it up and learn it. You sell the boat at the end and get most of that money back (see Budget tab), so the trip’s TRUE cost is far below the cash you float.

Sheet Budget Summary
A1: BUDGET SUMMARY — Perth → Exmouth → Rowley Shoals → Indonesia → Darwin
A2: Dry season • 2 crew • buying a cheap older 32–38ft cruiser • DIY & frugal • all USD (AUD × ~0.66)
A4: Category | B4: Low | C4: Likely | D4: High | E4: What it covers
A5: Vessel | B5: =SUMIF(Detail!$A:$A,$A5,Detail!$D:$D) -> 17400 | C5: =SUMIF(Detail!$A:$A,$A5,Detail!$E:$E) -> 30700 | D5: =SUMIF(Detail!$A:$A,$A5,Detail!$F:$F) -> 50500 | E5: Cheap older boat + survey + haul-out
A6: Refit & Equipment | B6: =SUMIF(Detail!$A:$A,$A6,Detail!$D:$D) -> 10400 | C6: =SUMIF(Detail!$A:$A,$A6,Detail!$E:$E) -> 20800 | D6: =SUMIF(Detail!$A:$A,$A6,Detail!$F:$F) -> 65500 | E6: Safety gear, rigging, sails, nav, power, tender (DIY/used)
A7: Insurance | B7: =SUMIF(Detail!$A:$A,$A7,Detail!$D:$D) -> 1500 | C7: =SUMIF(Detail!$A:$A,$A7,Detail!$E:$E) -> 2900 | D7: =SUMIF(Detail!$A:$A,$A7,Detail!$F:$F) -> 5500 | E7: Liability + travel/medical/evacuation
A8: Fuel & Propulsion | B8: =SUMIF(Detail!$A:$A,$A8,Detail!$D:$D) -> 1600 | C8: =SUMIF(Detail!$A:$A,$A8,Detail!$E:$E) -> 3100 | D8: =SUMIF(Detail!$A:$A,$A8,Detail!$F:$F) -> 5800 | E8: Diesel + engine service
A9: Berthing | B9: =SUMIF(Detail!$A:$A,$A9,Detail!$D:$D) -> 1000 | C9: =SUMIF(Detail!$A:$A,$A9,Detail!$E:$E) -> 2200 | D9: =SUMIF(Detail!$A:$A,$A9,Detail!$F:$F) -> 4500 | E9: Marina nights (mostly anchored)
A10: Provisions & Food | B10: =SUMIF(Detail!$A:$A,$A10,Detail!$D:$D) -> 7000 | C10: =SUMIF(Detail!$A:$A,$A10,Detail!$E:$E) -> 10700 | D10: =SUMIF(Detail!$A:$A,$A10,Detail!$F:$F) -> 16300 | E10: Groceries, local food, gas
A11: Customs, Permits & Visas | B11: =SUMIF(Detail!$A:$A,$A11,Detail!$D:$D) -> 700 | C11: =SUMIF(Detail!$A:$A,$A11,Detail!$E:$E) -> 2150 | D11: =SUMIF(Detail!$A:$A,$A11,Detail!$F:$F) -> 5000 | E11: Indonesia permit/visas + AU re-entry
A12: Comms & Connectivity | B12: =SUMIF(Detail!$A:$A,$A12,Detail!$D:$D) -> 1000 | C12: =SUMIF(Detail!$A:$A,$A12,Detail!$E:$E) -> 2000 | D12: =SUMIF(Detail!$A:$A,$A12,Detail!$F:$F) -> 3600 | E12: Starlink + SIMs
A13: Maintenance & Repairs | B13: =SUMIF(Detail!$A:$A,$A13,Detail!$D:$D) -> 2000 | C13: =SUMIF(Detail!$A:$A,$A13,Detail!$E:$E) -> 4500 | D13: =SUMIF(Detail!$A:$A,$A13,Detail!$F:$F) -> 9000 | E13: Running repairs on an old boat
A14: Activities & Personal | B14: =SUMIF(Detail!$A:$A,$A14,Detail!$D:$D) -> 1900 | C14: =SUMIF(Detail!$A:$A,$A14,Detail!$E:$E) -> 5100 | D14: =SUMIF(Detail!$A:$A,$A14,Detail!$F:$F) -> 11500 | E14: Diving, tours, flights home, meds
A16: CAPITAL (boat + refit) — mostly recoverable | B16: =SUM(B5:B6) -> 27800 | C16: =SUM(C5:C6) -> 51500 | D16: =SUM(D5:D6) -> 116000
A17: OPERATING (6-month running costs) | B17: =SUM(B7:B14) -> 16700 | C17: =SUM(C7:C14) -> 32650 | D17: =SUM(D7:D14) -> 61200
A18: Contingency (% of operating) | B18: =B17*$F$18 -> 2505 | C18: =C17*$F$18 -> 4897.5 | D18: =D17*$F$18 -> 9180 | F18: 0.15
A19: TOTAL CASH YOU MUST FLOAT | B19: =B16+B17+B18 -> 47005 | C19: =C16+C17+C18 -> 89047.5 | D19: =D16+D17+D18 -> 186380
A22: WHAT IT ACTUALLY COSTS YOU (you sell the boat at the end)
A23: Resale recovery rate on boat + refit (editable) | C23: 0.85 | E23: Cheap sound boats hold value; ~80–90% back
A24: Resale proceeds back (Likely) | C24: =C16*C23 -> 43775
A25: TRUE COST OF THE TRIP (Likely, after resale) | C25: =C19-C24 -> 45272.5
A28: How to read this: the big number ("cash you must float") is dominated by the boat — but you get ~85% of that back when you sell her in Darwin/Australia afterwards, so the trip’s TRUE cost is the smaller figure. Levers to go cheaper: smaller/older boat, skip the watermaker (carry water), liability-only insurance, anchor out, and DIY the refit. Levers that add up fast: a catamaran (1.5–2x everything), hull insurance, and marina living. Verify current Indonesia YachtERS permit + visa rules before departure — they change. Insurance note: many young budget cruisers run liability-only and self-insure the hull; that’s the cheap path but you carry the risk if the boat is lost.

Sheet Detail
A1: BUDGET DETAIL — shoestring version (older 32–38ft boat, DIY, anchor-out) | USD
A2: Blue = editable estimate. Low = lean/shoestring, Likely = realistic frugal, High = if things go sideways.
A3: Category | B3: Line item | C3: Notes / assumptions | D3: Low | E3: Likely | F3: High
A4: Vessel | B4: Boat — older 34–38ft fibreglass cruiser | C4: Capable older bluewater design. ~AUD $25–60k. | D4: 15000 | E4: 26000 | F4: 42000
A5: Vessel | B5: Pre-purchase survey | C5: Cheap insurance against a money-pit. | D5: 1200 | E5: 2200 | F5: 3500
A6: Vessel | B6: Pre-trip haul-out & antifoul (DIY where you can) | D6: 1200 | E6: 2500 | F6: 5000
A7: Refit & Equipment | B7: Standing rigging check / selective replacement | C7: Inspect; replace only what is due. | D7: 1000 | E7: 3500 | F7: 9000
A8: Refit & Equipment | B8: Sails (good used; reuse what is aboard) | D8: 0 | E8: 1500 | F8: 7000
A9: Refit & Equipment | B9: Liferaft (hire or used) + EPIRB + PLBs | C9: Non-negotiable offshore. | D9: 2000 | E9: 3500 | F9: 6000
A10: Refit & Equipment | B10: Safety gear (harnesses, jacklines, flares, fire, medical) | D10: 1200 | E10: 1800 | F10: 4000
A11: Refit & Equipment | B11: Ground tackle (anchor + extra chain) | C11: Boat usually has a main anchor already. | D11: 1000 | E11: 1200 | F11: 4500
A12: Refit & Equipment | B12: Fresh water — jerry cans / small used watermaker | C12: Skip the watermaker to save ~$4k; plan water stops. | D12: 300 | E12: 800 | F12: 8000
A13: Refit & Equipment | B13: Navigation — tablet + OpenCPN, used AIS, autopilot | C13: Tablet nav saves thousands vs a new plotter. | D13: 800 | E13: 1500 | F13: 7000
A14: Refit & Equipment | B14: Comms (used Starlink dish + handheld VHF) | D14: 800 | E14: 1800 | F14: 3500
A15: Refit & Equipment | B15: Power (solar panels + batteries) | C15: Top up existing system. | D15: 1500 | E15: 2000 | F15: 8000
A16: Refit & Equipment | B16: Dinghy + outboard (used) | C16: Often comes with the boat. | D16: 800 | E16: 1200 | F16: 4500
A17: Refit & Equipment | B17: Spares, tools & consumables | D17: 1000 | E17: 2000 | F17: 4000
A18: Insurance | B18: Third-party liability only (self-insure the hull) | C18: Hull cover is costly/hard for young crew on a cheap boat; liability is cheap. | D18: 300 | E18: 700 | F18: 1500
A19: Insurance | B19: Travel / medical & emergency evacuation (2 ppl, 6 mo) | C19: Do NOT skip evacuation cover. | D19: 1200 | E19: 2200 | F19: 4000
A20: Fuel & Propulsion | B20: Diesel (sail-heavy, small engine) | D20: 1200 | E20: 2200 | F20: 4000
A21: Fuel & Propulsion | B21: Engine service, oils & filters | D21: 400 | E21: 900 | F21: 1800
A22: Berthing | B22: Marina nights (mostly at anchor = free) | D22: 1000 | E22: 2200 | F22: 4500
A23: Provisions & Food | B23: Groceries (2 ppl, ~26 wks, cook aboard) | C23: ~$300–350/week for two. | D23: 6000 | E23: 8500 | F23: 12000
A24: Provisions & Food | B24: Local food / eating out (Indonesia is cheap) | D24: 800 | E24: 1800 | F24: 3500
A25: Provisions & Food | B25: Galley gas | D25: 200 | E25: 400 | F25: 800
A26: Customs, Permits & Visas | B26: Indonesia e-permit (YachtERS) & clearances (DIY) | C26: Clearance is free; small admin/port fees. | D26: 200 | E26: 500 | F26: 1200
A27: Customs, Permits & Visas | B27: Indonesia agent (only if a port requires it) | C27: Skip in DIY-friendly ports (Kupang, Bali). | D27: 0 | E27: 500 | F27: 1500
A28: Customs, Permits & Visas | B28: Visas — VOA + extension (2 people) | C28: ~US$35 pp / 30 days, extendable. | D28: 200 | E28: 450 | F28: 1000
A29: Customs, Permits & Visas | B29: Australia re-entry & biosecurity | C29: ABF / biosecurity at Darwin. | D29: 300 | E29: 700 | F29: 1300
A30: Comms & Connectivity | B30: Starlink Roam plan (6 months) | C30: ~$165/mo unlimited-ish. | D30: 800 | E30: 1500 | F30: 2400
A31: Comms & Connectivity | B31: Local SIMs / sat airtime | D31: 200 | E31: 500 | F31: 1200
A32: Maintenance & Repairs | B32: Running repairs & parts (old boat — budget for it) | C32: Older boats break; this is the line that saves the trip. | D32: 2000 | E32: 4500 | F32: 9000
A33: Activities & Personal | B33: Diving & snorkelling (own gear vs charter) | D33: 600 | E33: 1800 | F33: 4000
A34: Activities & Personal | B34: Tours & land travel | D34: 400 | E34: 1200 | F34: 3000
A35: Activities & Personal | B35: Flights / positioning (one-way home from Darwin) | D35: 600 | E35: 1400 | F35: 3000
A36: Activities & Personal | B36: Vaccinations & meds | D36: 300 | E36: 700 | F36: 1500
B37: TOTAL — gross cash outlay | D37: =SUM(D4:D36) -> 44500 | E37: =SUM(E4:E36) -> 84150 | F37: =SUM(F4:F36) -> 177200
