Workbook

Sheet Assumptions
A1: SipLocal Sonoma — Model Assumptions
A2: Blue cells = inputs you can change. All other sheets recalculate.
A4: REVENUE
A5: Premium tier price ($/winery/mo) | B5: 40 | C5: Owner input, 2026-06-11
A6: Premium wineries signed | B6: 24 | C6: Owner assumption — 5.6% of ~425 Sonoma County wineries
A7: Ultra-premium tier price ($/winery/mo) | B7: 150 | C7: Owner input, 2026-06-11
A8: Ultra-premium wineries signed | B8: 3 | C8: Owner assumption — capped slots
A9: VARIABLE / PROGRAM COSTS
A10: Referral budget ($/mo) | B10: 1000 | C10: Owner input — $1 per activated user → ~1,000 users/mo
A11: Concierge AI cost ($/mo) | B11: 50 | C11: Owner input — OpenAI/Gemini/Voyage/Upstash usage
A12: Stripe rate (% of revenue) | B12: 0.029 | C12: Source: stripe.com standard US card pricing
A13: Stripe per-transaction fee ($) | B13: 0.3 | C13: Source: stripe.com standard US card pricing
A14: FIXED MONTHLY COSTS
A15: Google Workspace Business Starter ($/mo) | B15: 7 | C15: Source: workspace.google.com pricing, 2026-06 — annual commitment, 1 user
A16: Firebase Blaze estimate ($/mo) | B16: 25 | C16: Estimate — Firestore/Functions/Storage at <25k MAU
A17: Vercel Pro — website hosting ($/mo) | B17: 20 | C17: Source: vercel.com pricing — commercial use requires Pro
A18: Google Maps APIs ($/mo) | B18: 25 | C18: Estimate — Distance Matrix + Places at current volume
A19: Attribution provider ($/mo) | B19: 0 | C19: ChottuLink free tier to 25k MAU
A20: ANNUAL / ONE-TIME COSTS
A21: Apple Developer Program ($/yr) | B21: 99 | C21: Source: developer.apple.com
A22: Domain ($/yr) | B22: 20 | C22: Estimate
A23: Google Play registration ($ one-time) | B23: 25 | C23: Source: play.google.com — one-time, month 1

Sheet Monthly P&L
A1: SipLocal Sonoma — Year 1 Monthly P&L ($)
B3: M1 | C3: M2 | D3: M3 | E3: M4 | F3: M5 | G3: M6 | H3: M7 | I3: M8 | J3: M9 | K3: M10 | L3: M11 | M3: M12 | N3: Year 1
A4: Premium subscriptions (24 × $40) | B4: =Assumptions!$B$5*Assumptions!$B$6 -> 960 | C4: =Assumptions!$B$5*Assumptions!$B$6 -> 960 | D4: =Assumptions!$B$5*Assumptions!$B$6 -> 960 | E4: =Assumptions!$B$5*Assumptions!$B$6 -> 960 | F4: =Assumptions!$B$5*Assumptions!$B$6 -> 960 | G4: =Assumptions!$B$5*Assumptions!$B$6 -> 960 | H4: =Assumptions!$B$5*Assumptions!$B$6 -> 960 | I4: =Assumptions!$B$5*Assumptions!$B$6 -> 960 | ... M4: =Assumptions!$B$5*Assumptions!$B$6 -> 960 | N4: =SUM(B4:M4) -> 11520
A5: Ultra-premium subscriptions (3 × $150) | B5: =Assumptions!$B$7*Assumptions!$B$8 -> 450 | C5: =Assumptions!$B$7*Assumptions!$B$8 -> 450 | D5: =Assumptions!$B$7*Assumptions!$B$8 -> 450 | E5: =Assumptions!$B$7*Assumptions!$B$8 -> 450 | F5: =Assumptions!$B$7*Assumptions!$B$8 -> 450 | G5: =Assumptions!$B$7*Assumptions!$B$8 -> 450 | H5: =Assumptions!$B$7*Assumptions!$B$8 -> 450 | I5: =Assumptions!$B$7*Assumptions!$B$8 -> 450 | ... M5: =Assumptions!$B$7*Assumptions!$B$8 -> 450 | N5: =SUM(B5:M5) -> 5400
A6: Total revenue | B6: =B4+B5 -> 1410 | C6: =C4+C5 -> 1410 | D6: =D4+D5 -> 1410 | E6: =E4+E5 -> 1410 | F6: =F4+F5 -> 1410 | G6: =G4+G5 -> 1410 | H6: =H4+H5 -> 1410 | I6: =I4+I5 -> 1410 | ... M6: =M4+M5 -> 1410 | N6: =SUM(B6:M6) -> 16920
A8: Referral payouts | B8: =Assumptions!$B$10 -> 1000 | C8: =Assumptions!$B$10 -> 1000 | D8: =Assumptions!$B$10 -> 1000 | E8: =Assumptions!$B$10 -> 1000 | F8: =Assumptions!$B$10 -> 1000 | G8: =Assumptions!$B$10 -> 1000 | H8: =Assumptions!$B$10 -> 1000 | I8: =Assumptions!$B$10 -> 1000 | ... M8: =Assumptions!$B$10 -> 1000 | N8: =SUM(B8:M8) -> 12000
A9: Concierge AI | B9: =Assumptions!$B$11 -> 50 | C9: =Assumptions!$B$11 -> 50 | D9: =Assumptions!$B$11 -> 50 | E9: =Assumptions!$B$11 -> 50 | F9: =Assumptions!$B$11 -> 50 | G9: =Assumptions!$B$11 -> 50 | H9: =Assumptions!$B$11 -> 50 | I9: =Assumptions!$B$11 -> 50 | ... M9: =Assumptions!$B$11 -> 50 | N9: =SUM(B9:M9) -> 600
A10: Stripe fees | B10: =B6*Assumptions!$B$12+(Assumptions!$B$6+Assumptions!$B$8)*Assumptions!$B$13 -> 48.99 | C10: =C6*Assumptions!$B$12+(Assumptions!$B$6+Assumptions!$B$8)*Assumptions!$B$13 -> 48.99 | D10: =D6*Assumptions!$B$12+(Assumptions!$B$6+Assumptions!$B$8)*Assumptions!$B$13 -> 48.99 | E10: =E6*Assumptions!$B$12+(Assumptions!$B$6+Assumptions!$B$8)*Assumptions!$B$13 -> 48.99 | F10: =F6*Assumptions!$B$12+(Assumptions!$B$6+Assumptions!$B$8)*Assumptions!$B$13 -> 48.99 | G10: =G6*Assumptions!$B$12+(Assumptions!$B$6+Assumptions!$B$8)*Assumptions!$B$13 -> 48.99 | H10: =H6*Assumptions!$B$12+(Assumptions!$B$6+Assumptions!$B$8)*Assumptions!$B$13 -> 48.99 | I10: =I6*Assumptions!$B$12+(Assumptions!$B$6+Assumptions!$B$8)*Assumptions!$B$13 -> 48.99 | ... M10: =M6*Assumptions!$B$12+(Assumptions!$B$6+Assumptions!$B$8)*Assumptions!$B$13 -> 48.99 | N10: =SUM(B10:M10) -> 587.88
A11: Google Workspace | B11: =Assumptions!$B$15 -> 7 | C11: =Assumptions!$B$15 -> 7 | D11: =Assumptions!$B$15 -> 7 | E11: =Assumptions!$B$15 -> 7 | F11: =Assumptions!$B$15 -> 7 | G11: =Assumptions!$B$15 -> 7 | H11: =Assumptions!$B$15 -> 7 | I11: =Assumptions!$B$15 -> 7 | ... M11: =Assumptions!$B$15 -> 7 | N11: =SUM(B11:M11) -> 84
A12: Firebase | B12: =Assumptions!$B$16 -> 25 | C12: =Assumptions!$B$16 -> 25 | D12: =Assumptions!$B$16 -> 25 | E12: =Assumptions!$B$16 -> 25 | F12: =Assumptions!$B$16 -> 25 | G12: =Assumptions!$B$16 -> 25 | H12: =Assumptions!$B$16 -> 25 | I12: =Assumptions!$B$16 -> 25 | ... M12: =Assumptions!$B$16 -> 25 | N12: =SUM(B12:M12) -> 300
A13: Vercel | B13: =Assumptions!$B$17 -> 20 | C13: =Assumptions!$B$17 -> 20 | D13: =Assumptions!$B$17 -> 20 | E13: =Assumptions!$B$17 -> 20 | F13: =Assumptions!$B$17 -> 20 | G13: =Assumptions!$B$17 -> 20 | H13: =Assumptions!$B$17 -> 20 | I13: =Assumptions!$B$17 -> 20 | ... M13: =Assumptions!$B$17 -> 20 | N13: =SUM(B13:M13) -> 240
A14: Google Maps APIs | B14: =Assumptions!$B$18 -> 25 | C14: =Assumptions!$B$18 -> 25 | D14: =Assumptions!$B$18 -> 25 | E14: =Assumptions!$B$18 -> 25 | F14: =Assumptions!$B$18 -> 25 | G14: =Assumptions!$B$18 -> 25 | H14: =Assumptions!$B$18 -> 25 | I14: =Assumptions!$B$18 -> 25 | ... M14: =Assumptions!$B$18 -> 25 | N14: =SUM(B14:M14) -> 300
A15: Attribution provider | B15: =Assumptions!$B$19 -> 0 | C15: =Assumptions!$B$19 -> 0 | D15: =Assumptions!$B$19 -> 0 | E15: =Assumptions!$B$19 -> 0 | F15: =Assumptions!$B$19 -> 0 | G15: =Assumptions!$B$19 -> 0 | H15: =Assumptions!$B$19 -> 0 | I15: =Assumptions!$B$19 -> 0 | ... M15: =Assumptions!$B$19 -> 0 | N15: =SUM(B15:M15) -> 0
A16: Apple Developer + domain (1/12) | B16: =(Assumptions!$B$21+Assumptions!$B$22)/12 -> 9.9166667 | C16: =(Assumptions!$B$21+Assumptions!$B$22)/12 -> 9.9166667 | D16: =(Assumptions!$B$21+Assumptions!$B$22)/12 -> 9.9166667 | E16: =(Assumptions!$B$21+Assumptions!$B$22)/12 -> 9.9166667 | F16: =(Assumptions!$B$21+Assumptions!$B$22)/12 -> 9.9166667 | G16: =(Assumptions!$B$21+Assumptions!$B$22)/12 -> 9.9166667 | H16: =(Assumptions!$B$21+Assumptions!$B$22)/12 -> 9.9166667 | I16: =(Assumptions!$B$21+Assumptions!$B$22)/12 -> 9.9166667 | ... M16: =(Assumptions!$B$21+Assumptions!$B$22)/12 -> 9.9166667 | N16: =SUM(B16:M16) -> 119
A17: Google Play (one-time) | B17: =Assumptions!$B$23 -> 25 | C17: =0 -> 0 | D17: =0 -> 0 | E17: =0 -> 0 | F17: =0 -> 0 | G17: =0 -> 0 | H17: =0 -> 0 | I17: =0 -> 0 | J17: =0 -> 0 | ... M17: =0 -> 0 | N17: =SUM(B17:M17) -> 25
A18: Total costs | B18: =SUM(B8:B17) -> 1210.9067 | C18: =SUM(C8:C17) -> 1185.9067 | D18: =SUM(D8:D17) -> 1185.9067 | E18: =SUM(E8:E17) -> 1185.9067 | F18: =SUM(F8:F17) -> 1185.9067 | G18: =SUM(G8:G17) -> 1185.9067 | H18: =SUM(H8:H17) -> 1185.9067 | I18: =SUM(I8:I17) -> 1185.9067 | ... M18: =SUM(M8:M17) -> 1185.9067 | N18: =SUM(B18:M18) -> 14255.88
A20: Net profit | B20: =B6-B18 -> 199.09333 | C20: =C6-C18 -> 224.09333 | D20: =D6-D18 -> 224.09333 | E20: =E6-E18 -> 224.09333 | F20: =F6-F18 -> 224.09333 | G20: =G6-G18 -> 224.09333 | H20: =H6-H18 -> 224.09333 | I20: =I6-I18 -> 224.09333 | ... M20: =M6-M18 -> 224.09333 | N20: =SUM(B20:M20) -> 2664.12
A21: Cumulative net profit | B21: =B20 -> 199.09333 | C21: =B21+C20 -> 423.18667 | D21: =C21+D20 -> 647.28 | E21: =D21+E20 -> 871.37333 | F21: =E21+F20 -> 1095.4667 | G21: =F21+G20 -> 1319.56 | H21: =G21+H20 -> 1543.6533 | I21: =H21+I20 -> 1767.7467 | J21: =I21+J20 -> 1991.84 | ... M21: =L21+M20 -> 2664.12 | N21: =N20 -> 2664.12
A23: Net margin | N23: =N20/N6 -> 0.1574539

Sheet Annual Summary
A1: SipLocal Sonoma — Year 1 Summary
B3: Year 1 ($) | C3: % of revenue
A4: Revenue — Premium tier | B4: ='Monthly P&L'!N4 -> 11520 | C4: =B4/$B$6 -> 0.68085106
A5: Revenue — Ultra-premium tier | B5: ='Monthly P&L'!N5 -> 5400 | C5: =B5/$B$6 -> 0.31914894
A6: Total revenue | B6: ='Monthly P&L'!N6 -> 16920 | C6: =B6/$B$6 -> 1
A7: Referral payouts | B7: ='Monthly P&L'!N8 -> 12000 | C7: =B7/$B$6 -> 0.70921986
A8: Concierge AI | B8: ='Monthly P&L'!N9 -> 600 | C8: =B8/$B$6 -> 0.035460993
A9: Stripe fees | B9: ='Monthly P&L'!N10 -> 587.88 | C9: =B9/$B$6 -> 0.034744681
A10: Infrastructure & tools (GWS, Firebase, Vercel, Maps, attribution) | B10: ='Monthly P&L'!N11+'Monthly P&L'!N12+'Monthly P&L'!N13+'Monthly P&L'!N14+'Monthly P&L'!N15 -> 924 | C10: =B10/$B$6 -> 0.054609929
A11: Annual & one-time fees (Apple, domain, Play) | B11: ='Monthly P&L'!N16+'Monthly P&L'!N17 -> 144 | C11: =B11/$B$6 -> 0.0085106383
A12: Total costs | B12: ='Monthly P&L'!N18 -> 14255.88 | C12: =B12/$B$6 -> 0.8425461
A13: Net profit | B13: ='Monthly P&L'!N20 -> 2664.12 | C13: =B13/$B$6 -> 0.1574539

Sheet Scenarios
A1: Year-1 net profit sensitivity
A2: Rows: premium wineries signed · Columns: monthly referral budget. Ultra-premium held at base assumptions.
A4: Premium wineries ↓ / Referral $/mo → | B4: 0 | C4: 500 | D4: 1000 | E4: 1500 | F4: 2000
A5: 12 | B5: =($A5*Assumptions!$B$5+Assumptions!$B$8*Assumptions!$B$7)*12*(1-Assumptions!$B$12)-($A5+Assumptions!$B$8)*Assumptions!$B$13*12-B$4*12-(Assumptions!$B$11+Assumptions!$B$15+Assumptions!$B$16+Assumptions!$B$17+Assumptions!$B$18+Assumptions!$B$19)*12-Assumptions!$B$21-Assumptions!$B$22-Assumptions!$B$23 -> 9114.36 | C5: =($A5*Assumptions!$B$5+Assumptions!$B$8*Assumptions!$B$7)*12*(1-Assumptions!$B$12)-($A5+Assumptions!$B$8)*Assumptions!$B$13*12-C$4*12-(Assumptions!$B$11+Assumptions!$B$15+Assumptions!$B$16+Assumptions!$B$17+Assumptions!$B$18+Assumptions!$B$19)*12-Assumptions!$B$21-Assumptions!$B$22-Assumptions!$B$23 -> 3114.36 | D5: =($A5*Assumptions!$B$5+Assumptions!$B$8*Assumptions!$B$7)*12*(1-Assumptions!$B$12)-($A5+Assumptions!$B$8)*Assumptions!$B$13*12-D$4*12-(Assumptions!$B$11+Assumptions!$B$15+Assumptions!$B$16+Assumptions!$B$17+Assumptions!$B$18+Assumptions!$B$19)*12-Assumptions!$B$21-Assumptions!$B$22-Assumptions!$B$23 -> -2885.64 | E5: =($A5*Assumptions!$B$5+Assumptions!$B$8*Assumptions!$B$7)*12*(1-Assumptions!$B$12)-($A5+Assumptions!$B$8)*Assumptions!$B$13*12-E$4*12-(Assumptions!$B$11+Assumptions!$B$15+Assumptions!$B$16+Assumptions!$B$17+Assumptions!$B$18+Assumptions!$B$19)*12-Assumptions!$B$21-Assumptions!$B$22-Assumptions!$B$23 -> -8885.64 | F5: =($A5*Assumptions!$B$5+Assumptions!$B$8*Assumptions!$B$7)*12*(1-Assumptions!$B$12)-($A5+Assumptions!$B$8)*Assumptions!$B$13*12-F$4*12-(Assumptions!$B$11+Assumptions!$B$15+Assumptions!$B$16+Assumptions!$B$17+Assumptions!$B$18+Assumptions!$B$19)*12-Assumptions!$B$21-Assumptions!$B$22-Assumptions!$B$23 -> -14885.64
A6: 18 | B6: =($A6*Assumptions!$B$5+Assumptions!$B$8*Assumptions!$B$7)*12*(1-Assumptions!$B$12)-($A6+Assumptions!$B$8)*Assumptions!$B$13*12-B$4*12-(Assumptions!$B$11+Assumptions!$B$15+Assumptions!$B$16+Assumptions!$B$17+Assumptions!$B$18+Assumptions!$B$19)*12-Assumptions!$B$21-Assumptions!$B$22-Assumptions!$B$23 -> 11889.24 | C6: =($A6*Assumptions!$B$5+Assumptions!$B$8*Assumptions!$B$7)*12*(1-Assumptions!$B$12)-($A6+Assumptions!$B$8)*Assumptions!$B$13*12-C$4*12-(Assumptions!$B$11+Assumptions!$B$15+Assumptions!$B$16+Assumptions!$B$17+Assumptions!$B$18+Assumptions!$B$19)*12-Assumptions!$B$21-Assumptions!$B$22-Assumptions!$B$23 -> 5889.24 | D6: =($A6*Assumptions!$B$5+Assumptions!$B$8*Assumptions!$B$7)*12*(1-Assumptions!$B$12)-($A6+Assumptions!$B$8)*Assumptions!$B$13*12-D$4*12-(Assumptions!$B$11+Assumptions!$B$15+Assumptions!$B$16+Assumptions!$B$17+Assumptions!$B$18+Assumptions!$B$19)*12-Assumptions!$B$21-Assumptions!$B$22-Assumptions!$B$23 -> -110.76 | E6: =($A6*Assumptions!$B$5+Assumptions!$B$8*Assumptions!$B$7)*12*(1-Assumptions!$B$12)-($A6+Assumptions!$B$8)*Assumptions!$B$13*12-E$4*12-(Assumptions!$B$11+Assumptions!$B$15+Assumptions!$B$16+Assumptions!$B$17+Assumptions!$B$18+Assumptions!$B$19)*12-Assumptions!$B$21-Assumptions!$B$22-Assumptions!$B$23 -> -6110.76 | F6: =($A6*Assumptions!$B$5+Assumptions!$B$8*Assumptions!$B$7)*12*(1-Assumptions!$B$12)-($A6+Assumptions!$B$8)*Assumptions!$B$13*12-F$4*12-(Assumptions!$B$11+Assumptions!$B$15+Assumptions!$B$16+Assumptions!$B$17+Assumptions!$B$18+Assumptions!$B$19)*12-Assumptions!$B$21-Assumptions!$B$22-Assumptions!$B$23 -> -12110.76
A7: 24 | B7: =($A7*Assumptions!$B$5+Assumptions!$B$8*Assumptions!$B$7)*12*(1-Assumptions!$B$12)-($A7+Assumptions!$B$8)*Assumptions!$B$13*12-B$4*12-(Assumptions!$B$11+Assumptions!$B$15+Assumptions!$B$16+Assumptions!$B$17+Assumptions!$B$18+Assumptions!$B$19)*12-Assumptions!$B$21-Assumptions!$B$22-Assumptions!$B$23 -> 14664.12 | C7: =($A7*Assumptions!$B$5+Assumptions!$B$8*Assumptions!$B$7)*12*(1-Assumptions!$B$12)-($A7+Assumptions!$B$8)*Assumptions!$B$13*12-C$4*12-(Assumptions!$B$11+Assumptions!$B$15+Assumptions!$B$16+Assumptions!$B$17+Assumptions!$B$18+Assumptions!$B$19)*12-Assumptions!$B$21-Assumptions!$B$22-Assumptions!$B$23 -> 8664.12 | D7: =($A7*Assumptions!$B$5+Assumptions!$B$8*Assumptions!$B$7)*12*(1-Assumptions!$B$12)-($A7+Assumptions!$B$8)*Assumptions!$B$13*12-D$4*12-(Assumptions!$B$11+Assumptions!$B$15+Assumptions!$B$16+Assumptions!$B$17+Assumptions!$B$18+Assumptions!$B$19)*12-Assumptions!$B$21-Assumptions!$B$22-Assumptions!$B$23 -> 2664.12 | E7: =($A7*Assumptions!$B$5+Assumptions!$B$8*Assumptions!$B$7)*12*(1-Assumptions!$B$12)-($A7+Assumptions!$B$8)*Assumptions!$B$13*12-E$4*12-(Assumptions!$B$11+Assumptions!$B$15+Assumptions!$B$16+Assumptions!$B$17+Assumptions!$B$18+Assumptions!$B$19)*12-Assumptions!$B$21-Assumptions!$B$22-Assumptions!$B$23 -> -3335.88 | F7: =($A7*Assumptions!$B$5+Assumptions!$B$8*Assumptions!$B$7)*12*(1-Assumptions!$B$12)-($A7+Assumptions!$B$8)*Assumptions!$B$13*12-F$4*12-(Assumptions!$B$11+Assumptions!$B$15+Assumptions!$B$16+Assumptions!$B$17+Assumptions!$B$18+Assumptions!$B$19)*12-Assumptions!$B$21-Assumptions!$B$22-Assumptions!$B$23 -> -9335.88
A8: 30 | B8: =($A8*Assumptions!$B$5+Assumptions!$B$8*Assumptions!$B$7)*12*(1-Assumptions!$B$12)-($A8+Assumptions!$B$8)*Assumptions!$B$13*12-B$4*12-(Assumptions!$B$11+Assumptions!$B$15+Assumptions!$B$16+Assumptions!$B$17+Assumptions!$B$18+Assumptions!$B$19)*12-Assumptions!$B$21-Assumptions!$B$22-Assumptions!$B$23 -> 17439 | C8: =($A8*Assumptions!$B$5+Assumptions!$B$8*Assumptions!$B$7)*12*(1-Assumptions!$B$12)-($A8+Assumptions!$B$8)*Assumptions!$B$13*12-C$4*12-(Assumptions!$B$11+Assumptions!$B$15+Assumptions!$B$16+Assumptions!$B$17+Assumptions!$B$18+Assumptions!$B$19)*12-Assumptions!$B$21-Assumptions!$B$22-Assumptions!$B$23 -> 11439 | D8: =($A8*Assumptions!$B$5+Assumptions!$B$8*Assumptions!$B$7)*12*(1-Assumptions!$B$12)-($A8+Assumptions!$B$8)*Assumptions!$B$13*12-D$4*12-(Assumptions!$B$11+Assumptions!$B$15+Assumptions!$B$16+Assumptions!$B$17+Assumptions!$B$18+Assumptions!$B$19)*12-Assumptions!$B$21-Assumptions!$B$22-Assumptions!$B$23 -> 5439 | E8: =($A8*Assumptions!$B$5+Assumptions!$B$8*Assumptions!$B$7)*12*(1-Assumptions!$B$12)-($A8+Assumptions!$B$8)*Assumptions!$B$13*12-E$4*12-(Assumptions!$B$11+Assumptions!$B$15+Assumptions!$B$16+Assumptions!$B$17+Assumptions!$B$18+Assumptions!$B$19)*12-Assumptions!$B$21-Assumptions!$B$22-Assumptions!$B$23 -> -561 | F8: =($A8*Assumptions!$B$5+Assumptions!$B$8*Assumptions!$B$7)*12*(1-Assumptions!$B$12)-($A8+Assumptions!$B$8)*Assumptions!$B$13*12-F$4*12-(Assumptions!$B$11+Assumptions!$B$15+Assumptions!$B$16+Assumptions!$B$17+Assumptions!$B$18+Assumptions!$B$19)*12-Assumptions!$B$21-Assumptions!$B$22-Assumptions!$B$23 -> -6561
A9: 36 | B9: =($A9*Assumptions!$B$5+Assumptions!$B$8*Assumptions!$B$7)*12*(1-Assumptions!$B$12)-($A9+Assumptions!$B$8)*Assumptions!$B$13*12-B$4*12-(Assumptions!$B$11+Assumptions!$B$15+Assumptions!$B$16+Assumptions!$B$17+Assumptions!$B$18+Assumptions!$B$19)*12-Assumptions!$B$21-Assumptions!$B$22-Assumptions!$B$23 -> 20213.88 | C9: =($A9*Assumptions!$B$5+Assumptions!$B$8*Assumptions!$B$7)*12*(1-Assumptions!$B$12)-($A9+Assumptions!$B$8)*Assumptions!$B$13*12-C$4*12-(Assumptions!$B$11+Assumptions!$B$15+Assumptions!$B$16+Assumptions!$B$17+Assumptions!$B$18+Assumptions!$B$19)*12-Assumptions!$B$21-Assumptions!$B$22-Assumptions!$B$23 -> 14213.88 | D9: =($A9*Assumptions!$B$5+Assumptions!$B$8*Assumptions!$B$7)*12*(1-Assumptions!$B$12)-($A9+Assumptions!$B$8)*Assumptions!$B$13*12-D$4*12-(Assumptions!$B$11+Assumptions!$B$15+Assumptions!$B$16+Assumptions!$B$17+Assumptions!$B$18+Assumptions!$B$19)*12-Assumptions!$B$21-Assumptions!$B$22-Assumptions!$B$23 -> 8213.88 | E9: =($A9*Assumptions!$B$5+Assumptions!$B$8*Assumptions!$B$7)*12*(1-Assumptions!$B$12)-($A9+Assumptions!$B$8)*Assumptions!$B$13*12-E$4*12-(Assumptions!$B$11+Assumptions!$B$15+Assumptions!$B$16+Assumptions!$B$17+Assumptions!$B$18+Assumptions!$B$19)*12-Assumptions!$B$21-Assumptions!$B$22-Assumptions!$B$23 -> 2213.88 | F9: =($A9*Assumptions!$B$5+Assumptions!$B$8*Assumptions!$B$7)*12*(1-Assumptions!$B$12)-($A9+Assumptions!$B$8)*Assumptions!$B$13*12-F$4*12-(Assumptions!$B$11+Assumptions!$B$15+Assumptions!$B$16+Assumptions!$B$17+Assumptions!$B$18+Assumptions!$B$19)*12-Assumptions!$B$21-Assumptions!$B$22-Assumptions!$B$23 -> -3786.12
A11: Base case = 24 premium / $1,000 referral budget. Negative cells = annual loss.

Sheet Winery ROI
A1: Winery ROI — does a subscription pay for itself?
A2: Funnel: MAU → profile views → high-intent actions (directions/booking taps) → visits → tasting-room revenue. Blue = inputs.
A4: INPUTS
A5: App MAU (in-region) | B5: 1000 | C5: Owner scenario input
A6: Avg winery-profile views per user per month | B6: 5 | C6: Estimate — tune once telemetry exists
A7: Total listed wineries (incl. free tier) | B7: 80 | C7: Estimate — free tier seeds directory
A8: Premium visibility multiplier (vs free listing) | B8: 3 | C8: Concierge boost + richer card
A9: Ultra-premium visibility multiplier | B9: 5 | C9: Higher boost cap + IG/editorial halo
A10: View → high-intent action rate | B10: 0.04 | C10: Directions tap or booking-link click
A11: High-intent action → actual visit rate | B11: 0.5 | C11: Estimate
A12: Avg tasting-room revenue per visiting party ($) | B12: 20 | C12: Owner input — conservative: tasting fee often waived with bottle purchase
A14: PER-WINERY FUNNEL (monthly) | B14: Free | C14: Premium | D14: Ultra-prem.
A15: Total profile views across app | B15: =$B$5*$B$6 -> 5000
A16: Total visibility weight (free×1 + prem×mult + ultra×mult) | B16: =($B$7-Assumptions!$B$6-Assumptions!$B$8)*1+Assumptions!$B$6*$B$8+Assumptions!$B$8*$B$9 -> 140
A17: Profile views per winery | B17: =$B$15*1/$B$16 -> 35.714286 | C17: =$B$15*$B$8/$B$16 -> 107.14286 | D17: =$B$15*$B$9/$B$16 -> 178.57143
A18: High-intent actions per winery | B18: =B17*$B$10 -> 1.4285714 | C18: =C17*$B$10 -> 4.2857143 | D18: =D17*$B$10 -> 7.1428571
A19: Estimated visits per winery | B19: =B18*$B$11 -> 0.71428571 | C19: =C18*$B$11 -> 2.1428571 | D19: =D18*$B$11 -> 3.5714286
A20: Estimated tasting-room revenue driven | B20: =B19*$B$12 -> 14.285714 | C20: =C19*$B$12 -> 42.857143 | D20: =D19*$B$12 -> 71.428571
A21: Subscription cost | B21: =0 -> 0 | C21: =Assumptions!$B$5 -> 40 | D21: =Assumptions!$B$7 -> 150
A22: ROI multiple (revenue ÷ cost) | B22: ="n/a" -> n/a | C22: =C20/C21 -> 1.0714286 | D22: =D20/D21 -> 0.47619048
A23: Visits needed to break even | B23: ="n/a" -> n/a | C23: =Assumptions!$B$5/$B$12 -> 2 | D23: =Assumptions!$B$7/$B$12 -> 7.5
A25: MAU SENSITIVITY — Premium winery, monthly | B25: Views | C25: Visits | D25: Revenue | E25: ROI
A26: 1000 | B26: =$A26*$B$6*$B$8/$B$16 -> 107.14286 | C26: =B26*$B$10*$B$11 -> 2.1428571 | D26: =C26*$B$12 -> 42.857143 | E26: =D26/Assumptions!$B$5 -> 1.0714286
A27: 2500 | B27: =$A27*$B$6*$B$8/$B$16 -> 267.85714 | C27: =B27*$B$10*$B$11 -> 5.3571429 | D27: =C27*$B$12 -> 107.14286 | E27: =D27/Assumptions!$B$5 -> 2.6785714
A28: 5000 | B28: =$A28*$B$6*$B$8/$B$16 -> 535.71429 | C28: =B28*$B$10*$B$11 -> 10.714286 | D28: =C28*$B$12 -> 214.28571 | E28: =D28/Assumptions!$B$5 -> 5.3571429
A29: 10000 | B29: =$A29*$B$6*$B$8/$B$16 -> 1071.4286 | C29: =B29*$B$10*$B$11 -> 21.428571 | D29: =C29*$B$12 -> 428.57143 | E29: =D29/Assumptions!$B$5 -> 10.714286
A31: Renewal rule of thumb: a Premium winery needs ROI ≥ ~3x to feel obviously worth it; 1x is the floor.
